[
  {
    "trial": 1,
    "optimal_params": {
      "alpha": -1.2347166371772065,
      "beta": -0.8894685061346881,
      "coupling_coeff": -0.9129893849288963,
      "noise_level": 0.001,
      "p": 2.289875311193954
    },
    "maxcut_value": 690.0
  },
  {
    "trial": 2,
    "optimal_params": {
      "alpha": -1.3795642755413287,
      "beta": -0.8550819676486929,
      "coupling_coeff": -0.7831739785959674,
      "noise_level": 0.001,
      "p": 1.742219015969293
    },
    "maxcut_value": 668.0
  },
  {
    "trial": 3,
    "optimal_params": {
      "alpha": -0.8299600944130051,
      "beta": -1.8570579420784963,
      "coupling_coeff": -1.0,
      "noise_level": 0.001,
      "p": 3.0
    },
    "maxcut_value": 712.0
  },
  {
    "trial": 4,
    "optimal_params": {
      "alpha": -0.0007345986085776793,
      "beta": -0.558368886122156,
      "coupling_coeff": -0.4739641408312602,
      "noise_level": 0.1887897107054874,
      "p": 2.248476305141076
    },
    "maxcut_value": 672.0
  },
  {
    "trial": 5,
    "optimal_params": {
      "alpha": -0.5926343115562984,
      "beta": -0.3803443228344634,
      "coupling_coeff": -0.07988445124691312,
      "noise_level": 0.06862847052137497,
      "p": 1.5006693846381793
    },
    "maxcut_value": 570.0
  },
  {
    "trial": 6,
    "optimal_params": {
      "alpha": 2.0,
      "beta": -0.01,
      "coupling_coeff": -1.0,
      "noise_level": 2.2416907047068193,
      "p": 2.8103366877024154
    },
    "maxcut_value": 686.0
  },
  {
    "trial": 7,
    "optimal_params": {
      "alpha": 0.27439815391555705,
      "beta": -0.01,
      "coupling_coeff": -1.0,
      "noise_level": 0.001,
      "p": 3.0
    },
    "maxcut_value": 711.0
  },
  {
    "trial": 8,
    "optimal_params": {
      "alpha": -1.8152163960688175,
      "beta": -2.0,
      "coupling_coeff": -0.906278584094269,
      "noise_level": 0.001,
      "p": 2.0644203717393808
    },
    "maxcut_value": 711.0
  },
  {
    "trial": 9,
    "optimal_params": {
      "alpha": 1.7047570400312295,
      "beta": -1.6093730963968398,
      "coupling_coeff": -0.962111910963559,
      "noise_level": 0.001,
      "p": 1.001
    },
    "maxcut_value": 712.0
  },
  {
    "trial": 10,
    "optimal_params": {
      "alpha": -0.5513679759811129,
      "beta": -0.8488350812991582,
      "coupling_coeff": -0.7900701162639971,
      "noise_level": 0.001,
      "p": 2.089745770703674
    },
    "maxcut_value": 698.0
  }
]